nemo_bldc/__init__.py
nemo_bldc/nemo.py
nemo_bldc/doc/BrushlessMotorPhysics.pdf
nemo_bldc/doc/__init__.py
nemo_bldc/doc/user_manual.pdf
nemo_bldc/gui/__init__.py
nemo_bldc/gui/abstract_tab.py
nemo_bldc/gui/gui_compare_motors.py
nemo_bldc/gui/gui_simulation.py
nemo_bldc/gui/gui_single_motor_perf.py
nemo_bldc/gui/main_window.py
nemo_bldc/gui/motor_creation_helper.py
nemo_bldc/gui/utils.py
nemo_bldc/gui/widget_motor_creation.py
nemo_bldc/gui/widget_pi_config.py
nemo_bldc/gui/widget_signal_config.py
nemo_bldc/physics/__init__.py
nemo_bldc/physics/battery.py
nemo_bldc/physics/motor.py
nemo_bldc/ressources/__init__.py
nemo_bldc/ressources/abstract_tab.glade
nemo_bldc/ressources/compare_tab.glade
nemo_bldc/ressources/logo.svg
nemo_bldc/ressources/logo_readme.svg
nemo_bldc/ressources/main_window.glade
nemo_bldc/ressources/motor_creation_helper.glade
nemo_bldc/ressources/motor_creation_widget.glade
nemo_bldc/ressources/motor_library.json
nemo_bldc/ressources/pi_config_widget.glade
nemo_bldc/ressources/signal_config_widget.glade
nemo_bldc/ressources/simulation_tab.glade
nemo_bldc/ressources/single_motor_tab.glade
nemo_bldc/ressources/utils.py
nemo_bldc/simulation/__init__.py
nemo_bldc/simulation/pi_controller.py
nemo_bldc/simulation/signal.py
nemo_bldc/simulation/simulate.py
nemo_bldc/simulation/space_transforms.py
nemo_bldc-1.1.0.dist-info/LICENSE
nemo_bldc-1.1.0.dist-info/METADATA
nemo_bldc-1.1.0.dist-info/WHEEL
nemo_bldc-1.1.0.dist-info/entry_points.txt
nemo_bldc-1.1.0.dist-info/top_level.txt
nemo_bldc-1.1.0.dist-info/RECORD
