Metadata-Version: 2.1
Name: nemo-bldc
Version: 1.1.0
Summary: A tool to evaluate and compare brushless motors
Author: Matthieu Vigne
License: MIT
Project-URL: Source, https://github.com/matthieuvigne/nemo_bldc
License-File: LICENSE
Requires-Dist: pycairo
Requires-Dist: pytest
Requires-Dist: numpy
Requires-Dist: matplotlib
Requires-Dist: PyGObject
